setup.py
src/protodict.py
src/protodict.egg-info/PKG-INFO
src/protodict.egg-info/SOURCES.txt
src/protodict.egg-info/dependency_links.txt
src/protodict.egg-info/requires.txt
src/protodict.egg-info/top_level.txt