Metadata-Version: 1.1
Name: protodict
Version: 1.0.0
Summary: a small Python library for 2 ways conversion between dicts and protocol buffers.
Home-page: https://github.com/3kwa/protodict
Author: Eugene Van den Bulke
Author-email: eugene.vandenbulke@gmail.com
License: Public Domain
Keywords: protobuf,dict
Platform: UNKNOWN
Classifier: Programming Language :: Python
Classifier: Development Status :: 5 - Production/Stable
Classifier: Intended Audience :: Developers
Classifier: License :: Public Domain
Classifier: Operating System :: OS Independent
Classifier: Topic :: Software Development :: Libraries :: Python Modules
